bolt12/.gitignore
bolt12/__init__.py
bolt12/bolt12.py
bolt12/fundamentals.py
bolt12/generated.py
bolt12/key.py
bolt12/preamble.py
bolt12-0.1.3.dist-info/WHEEL
bolt12-0.1.3.dist-info/METADATA
bolt12-0.1.3.dist-info/RECORD
